[
  {
    "Company": "Samsung",
    "ModelName": "Galaxy S21",
    "Ram": "8GB",
    "Storage": "128GB",
    "Battery": "5000mAh",
    "CreatedDate": "2025-06-03T13:00:43.2679479+05:00"
  },
  {
    "Company": "Samsung",
    "ModelName": "Galaxy A52",
    "Ram": "6GB",
    "Storage": "256GB",
    "Battery": "4500mAh",
    "CreatedDate": "2025-06-03T13:00:43.2837294+05:00"
  },
  {
    "Company": "Samsung",
    "ModelName": "Note 20",
    "Ram": "12GB",
    "Storage": "512GB",
    "Battery": "5500mAh",
    "CreatedDate": "2025-06-03T13:00:43.2837294+05:00"
  },
  {
    "Company": "Samsung",
    "ModelName": "Note 24 Ultra",
    "Ram": "4GB",
    "Storage": "64GB",
    "Battery": "4500mAh",
    "CreatedDate": "2025-06-03T13:00:43.2837294+05:00"
  },
  {
    "Company": "Samsung",
    "ModelName": "Note 25",
    "Ram": "8GB",
    "Storage": "128GB",
    "Battery": "5000mAh",
    "CreatedDate": "2025-06-03T13:00:43.2837294+05:00"
  },
  {
    "Company": "Apple",
    "ModelName": "iPhone 13",
    "Ram": "6GB",
    "Storage": "256GB",
    "Battery": "4500mAh",
    "CreatedDate": "2025-06-03T13:00:43.2837294+05:00"
  },
  {
    "Company": "Apple",
    "ModelName": "iPhone 14",
    "Ram": "4GB",
    "Storage": "64GB",
    "Battery": "5000mAh",
    "CreatedDate": "2025-06-03T13:00:43.2837294+05:00"
  },
  {
    "Company": "Apple",
    "ModelName": "iPhone SE",
    "Ram": "8GB",
    "Storage": "128GB",
    "Battery": "4500mAh",
    "CreatedDate": "2025-06-03T13:00:43.2837294+05:00"
  },
  {
    "Company": "Apple",
    "ModelName": "iPhone 15",
    "Ram": "12GB",
    "Storage": "512GB",
    "Battery": "5500mAh",
    "CreatedDate": "2025-06-03T13:00:43.2837294+05:00"
  },
  {
    "Company": "Apple",
    "ModelName": "iPhone 16",
    "Ram": "6GB",
    "Storage": "256GB",
    "Battery": "5000mAh",
    "CreatedDate": "2025-06-03T13:00:43.2837294+05:00"
  },
  {
    "Company": "Huawei",
    "ModelName": "P50",
    "Ram": "4GB",
    "Storage": "64GB",
    "Battery": "4500mAh",
    "CreatedDate": "2025-06-03T13:00:43.2837294+05:00"
  },
  {
    "Company": "Huawei",
    "ModelName": "Mate 40",
    "Ram": "8GB",
    "Storage": "128GB",
    "Battery": "5000mAh",
    "CreatedDate": "2025-06-03T13:00:43.2837294+05:00"
  },
  {
    "Company": "Huawei",
    "ModelName": "Nova 8",
    "Ram": "12GB",
    "Storage": "512GB",
    "Battery": "5500mAh",
    "CreatedDate": "2025-06-03T13:00:43.2837294+05:00"
  },
  {
    "Company": "Huawei",
    "ModelName": "P40 Pro",
    "Ram": "6GB",
    "Storage": "256GB",
    "Battery": "5000mAh",
    "CreatedDate": "2025-06-03T13:00:43.2837294+05:00"
  },
  {
    "Company": "Huawei",
    "ModelName": "Mate X2",
    "Ram": "8GB",
    "Storage": "128GB",
    "Battery": "4500mAh",
    "CreatedDate": "2025-06-03T13:00:43.2837294+05:00"
  },
  {
    "Company": "Redmi",
    "ModelName": "Redmi Note 13 Pro+ 5G",
    "Ram": "6GB",
    "Storage": "256GB",
    "Battery": "5500mAh",
    "CreatedDate": "2025-06-03T13:00:43.2837294+05:00"
  },
  {
    "Company": "Redmi",
    "ModelName": "Redmi Note 13",
    "Ram": "4GB",
    "Storage": "64GB",
    "Battery": "4500mAh",
    "CreatedDate": "2025-06-03T13:00:43.2837294+05:00"
  },
  {
    "Company": "Redmi",
    "ModelName": "Redmi 13C",
    "Ram": "8GB",
    "Storage": "128GB",
    "Battery": "5000mAh",
    "CreatedDate": "2025-06-03T13:00:43.2837294+05:00"
  },
  {
    "Company": "Redmi",
    "ModelName": "Redmi Note 14 Pro",
    "Ram": "12GB",
    "Storage": "512GB",
    "Battery": "5500mAh",
    "CreatedDate": "2025-06-03T13:00:43.2837294+05:00"
  },
  {
    "Company": "Redmi",
    "ModelName": "Redmi 12",
    "Ram": "6GB",
    "Storage": "256GB",
    "Battery": "5000mAh",
    "CreatedDate": "2025-06-03T13:00:43.2837294+05:00"
  },
  {
    "Company": "Infinix",
    "ModelName": "Infinix Zero 30 5G",
    "Ram": "8GB",
    "Storage": "128GB",
    "Battery": "5000mAh",
    "CreatedDate": "2025-06-03T13:00:43.2837294+05:00"
  },
  {
    "Company": "Infinix",
    "ModelName": "Infinix Note 40 Pro",
    "Ram": "6GB",
    "Storage": "256GB",
    "Battery": "4500mAh",
    "CreatedDate": "2025-06-03T13:00:43.2837294+05:00"
  },
  {
    "Company": "Infinix",
    "ModelName": "Infinix Smart 8 Plus",
    "Ram": "4GB",
    "Storage": "64GB",
    "Battery": "4500mAh",
    "CreatedDate": "2025-06-03T13:00:43.2837294+05:00"
  },
  {
    "Company": "Infinix",
    "ModelName": "Infinix Zero 40",
    "Ram": "12GB",
    "Storage": "512GB",
    "Battery": "5500mAh",
    "CreatedDate": "2025-06-03T13:00:43.2837294+05:00"
  },
  {
    "Company": "Infinix",
    "ModelName": "Infinix Smart 9",
    "Ram": "8GB",
    "Storage": "128GB",
    "Battery": "5000mAh",
    "CreatedDate": "2025-06-03T13:00:43.2837294+05:00"
  },
  {
    "Company": "Samsung",
    "ModelName": "Galaxy A52",
    "Ram": "6GB",
    "Storage": "128GB",
    "Battery": "4500mAh",
    "CreatedDate": "2025-06-03T13:00:43.2837294+05:00"
  },
  {
    "Company": "Apple",
    "ModelName": "iPhone SE",
    "Ram": "4GB",
    "Storage": "64GB",
    "Battery": "4500mAh",
    "CreatedDate": "2025-06-03T13:00:43.2837294+05:00"
  },
  {
    "Company": "Huawei",
    "ModelName": "P50",
    "Ram": "6GB",
    "Storage": "256GB",
    "Battery": "5000mAh",
    "CreatedDate": "2025-06-03T13:00:43.2837294+05:00"
  }
]